{
	"start":	{
		"connected":	[{
				"socket":	6,
				"local_host":	"192.168.6.1",
				"local_port":	33198,
				"remote_host":	"192.168.15.1",
				"remote_port":	5007
			}],
		"version":	"iperf 3.6",
		"system_info":	"Linux ba-thesis 4.19.0-23-amd64 #1 SMP Debian 4.19.269-1 (2022-12-20) x86_64",
		"timestamp":	{
			"time":	"Sat, 03 Jun 2023 15:16:44 GMT",
			"timesecs":	1685805404
		},
		"connecting_to":	{
			"host":	"h0",
			"port":	5007
		},
		"cookie":	"ic5kgb4gb7ry34lm2jh2hk2nea4rphhm2xnd",
		"tcp_mss_default":	1448,
		"sock_bufsize":	0,
		"sndbuf_actual":	87380,
		"rcvbuf_actual":	87380,
		"test_start":	{
			"protocol":	"TCP",
			"num_streams":	1,
			"blksize":	131072,
			"omit":	0,
			"duration":	0,
			"bytes":	210240512,
			"blocks":	0,
			"reverse":	0,
			"tos":	0
		}
	},
	"intervals":	[{
			"streams":	[{
					"socket":	6,
					"start":	0,
					"end":	1.0001239776611328,
					"seconds":	1.0001239776611328,
					"bytes":	1253968,
					"bits_per_second":	10030500.442015206,
					"retransmits":	0,
					"snd_cwnd":	266432,
					"rtt":	141191,
					"rttvar":	5700,
					"pmtu":	1500,
					"omitted":	false
				}],
			"sum":	{
				"start":	0,
				"end":	1.0001239776611328,
				"seconds":	1.0001239776611328,
				"bytes":	1253968,
				"bits_per_second":	10030500.442015206,
				"retransmits":	0,
				"omitted":	false
			}
		}, {
			"streams":	[{
					"socket":	6,
					"start":	1.0001239776611328,
					"end":	2.0000679492950439,
					"seconds":	0.99994397163391113,
					"bytes":	4105080,
					"bits_per_second":	32842480.110498898,
					"retransmits":	0,
					"snd_cwnd":	495216,
					"rtt":	131940,
					"rttvar":	793,
					"pmtu":	1500,
					"omitted":	false
				}],
			"sum":	{
				"start":	1.0001239776611328,
				"end":	2.0000679492950439,
				"seconds":	0.99994397163391113,
				"bytes":	4105080,
				"bits_per_second":	32842480.110498898,
				"retransmits":	0,
				"omitted":	false
			}
		}, {
			"streams":	[{
					"socket":	6,
					"start":	2.0000679492950439,
					"end":	3.0000839233398438,
					"seconds":	1.0000159740447998,
					"bytes":	4764200,
					"bits_per_second":	38112991.181371413,
					"retransmits":	0,
					"snd_cwnd":	687800,
					"rtt":	140313,
					"rttvar":	3477,
					"pmtu":	1500,
					"omitted":	false
				}],
			"sum":	{
				"start":	2.0000679492950439,
				"end":	3.0000839233398438,
				"seconds":	1.0000159740447998,
				"bytes":	4764200,
				"bits_per_second":	38112991.181371413,
				"retransmits":	0,
				"omitted":	false
			}
		}, {
			"streams":	[{
					"socket":	6,
					"start":	3.0000839233398438,
					"end":	4.0000920295715332,
					"seconds":	1.0000081062316895,
					"bytes":	5242880,
					"bits_per_second":	41942700.0027561,
					"retransmits":	0,
					"snd_cwnd":	933960,
					"rtt":	145761,
					"rttvar":	32,
					"pmtu":	1500,
					"omitted":	false
				}],
			"sum":	{
				"start":	3.0000839233398438,
				"end":	4.0000920295715332,
				"seconds":	1.0000081062316895,
				"bytes":	5242880,
				"bits_per_second":	41942700.0027561,
				"retransmits":	0,
				"omitted":	false
			}
		}, {
			"streams":	[{
					"socket":	6,
					"start":	4.0000920295715332,
					"end":	5.0001480579376221,
					"seconds":	1.0000560283660889,
					"bytes":	6553600,
					"bits_per_second":	52425862.6645741,
					"retransmits":	0,
					"snd_cwnd":	1216320,
					"rtt":	145190,
					"rttvar":	336,
					"pmtu":	1500,
					"omitted":	false
				}],
			"sum":	{
				"start":	4.0000920295715332,
				"end":	5.0001480579376221,
				"seconds":	1.0000560283660889,
				"bytes":	6553600,
				"bits_per_second":	52425862.6645741,
				"retransmits":	0,
				"omitted":	false
			}
		}, {
			"streams":	[{
					"socket":	6,
					"start":	5.0001480579376221,
					"end":	6.0000669956207275,
					"seconds":	0.99991893768310547,
					"bytes":	9175040,
					"bits_per_second":	73406270.482359886,
					"retransmits":	0,
					"snd_cwnd":	1597144,
					"rtt":	211273,
					"rttvar":	235,
					"pmtu":	1500,
					"omitted":	false
				}],
			"sum":	{
				"start":	5.0001480579376221,
				"end":	6.0000669956207275,
				"seconds":	0.99991893768310547,
				"bytes":	9175040,
				"bits_per_second":	73406270.482359886,
				"retransmits":	0,
				"omitted":	false
			}
		}, {
			"streams":	[{
					"socket":	6,
					"start":	6.0000669956207275,
					"end":	7.0000269412994385,
					"seconds":	0.99995994567871094,
					"bytes":	9175040,
					"bits_per_second":	73403260.117764428,
					"retransmits":	0,
					"snd_cwnd":	1941768,
					"rtt":	239739,
					"rttvar":	6661,
					"pmtu":	1500,
					"omitted":	false
				}],
			"sum":	{
				"start":	6.0000669956207275,
				"end":	7.0000269412994385,
				"seconds":	0.99995994567871094,
				"bytes":	9175040,
				"bits_per_second":	73403260.117764428,
				"retransmits":	0,
				"omitted":	false
			}
		}, {
			"streams":	[{
					"socket":	6,
					"start":	7.0000269412994385,
					"end":	8.0000479221344,
					"seconds":	1.0000209808349609,
					"bytes":	9175040,
					"bits_per_second":	73398780.032309815,
					"retransmits":	0,
					"snd_cwnd":	2338520,
					"rtt":	310483,
					"rttvar":	3651,
					"pmtu":	1500,
					"omitted":	false
				}],
			"sum":	{
				"start":	7.0000269412994385,
				"end":	8.0000479221344,
				"seconds":	1.0000209808349609,
				"bytes":	9175040,
				"bits_per_second":	73398780.032309815,
				"retransmits":	0,
				"omitted":	false
			}
		}, {
			"streams":	[{
					"socket":	6,
					"start":	8.0000479221344,
					"end":	9.000114917755127,
					"seconds":	1.0000669956207275,
					"bytes":	9175040,
					"bits_per_second":	73395402.8294289,
					"retransmits":	0,
					"snd_cwnd":	2755544,
					"rtt":	342217,
					"rttvar":	633,
					"pmtu":	1500,
					"omitted":	false
				}],
			"sum":	{
				"start":	8.0000479221344,
				"end":	9.000114917755127,
				"seconds":	1.0000669956207275,
				"bytes":	9175040,
				"bits_per_second":	73395402.8294289,
				"retransmits":	0,
				"omitted":	false
			}
		}, {
			"streams":	[{
					"socket":	6,
					"start":	9.000114917755127,
					"end":	10.000114917755127,
					"seconds":	1,
					"bytes":	9175040,
					"bits_per_second":	73400320,
					"retransmits":	0,
					"snd_cwnd":	3169672,
					"rtt":	389007,
					"rttvar":	705,
					"pmtu":	1500,
					"omitted":	false
				}],
			"sum":	{
				"start":	9.000114917755127,
				"end":	10.000114917755127,
				"seconds":	1,
				"bytes":	9175040,
				"bits_per_second":	73400320,
				"retransmits":	0,
				"omitted":	false
			}
		}, {
			"streams":	[{
					"socket":	6,
					"start":	10.000114917755127,
					"end":	11.00009298324585,
					"seconds":	0.99997806549072266,
					"bytes":	7864320,
					"bits_per_second":	62915940.030270286,
					"retransmits":	0,
					"snd_cwnd":	2334176,
					"rtt":	321070,
					"rttvar":	4447,
					"pmtu":	1500,
					"omitted":	false
				}],
			"sum":	{
				"start":	10.000114917755127,
				"end":	11.00009298324585,
				"seconds":	0.99997806549072266,
				"bytes":	7864320,
				"bits_per_second":	62915940.030270286,
				"retransmits":	0,
				"omitted":	false
			}
		}, {
			"streams":	[{
					"socket":	6,
					"start":	11.00009298324585,
					"end":	12.000107049942017,
					"seconds":	1.000014066696167,
					"bytes":	9175040,
					"bits_per_second":	73399287.514523655,
					"retransmits":	0,
					"snd_cwnd":	2547032,
					"rtt":	289291,
					"rttvar":	4133,
					"pmtu":	1500,
					"omitted":	false
				}],
			"sum":	{
				"start":	11.00009298324585,
				"end":	12.000107049942017,
				"seconds":	1.000014066696167,
				"bytes":	9175040,
				"bits_per_second":	73399287.514523655,
				"retransmits":	0,
				"omitted":	false
			}
		}, {
			"streams":	[{
					"socket":	6,
					"start":	12.000107049942017,
					"end":	13.000080108642578,
					"seconds":	0.99997305870056152,
					"bytes":	9175040,
					"bits_per_second":	73402297.55327785,
					"retransmits":	0,
					"snd_cwnd":	2716448,
					"rtt":	354138,
					"rttvar":	496,
					"pmtu":	1500,
					"omitted":	false
				}],
			"sum":	{
				"start":	12.000107049942017,
				"end":	13.000080108642578,
				"seconds":	0.99997305870056152,
				"bytes":	9175040,
				"bits_per_second":	73402297.55327785,
				"retransmits":	0,
				"omitted":	false
			}
		}, {
			"streams":	[{
					"socket":	6,
					"start":	13.000080108642578,
					"end":	14.00012993812561,
					"seconds":	1.0000498294830322,
					"bytes":	7864320,
					"bits_per_second":	62911425.156207643,
					"retransmits":	0,
					"snd_cwnd":	2859800,
					"rtt":	347650,
					"rttvar":	982,
					"pmtu":	1500,
					"omitted":	false
				}],
			"sum":	{
				"start":	13.000080108642578,
				"end":	14.00012993812561,
				"seconds":	1.0000498294830322,
				"bytes":	7864320,
				"bits_per_second":	62911425.156207643,
				"retransmits":	0,
				"omitted":	false
			}
		}, {
			"streams":	[{
					"socket":	6,
					"start":	14.00012993812561,
					"end":	15.000135898590088,
					"seconds":	1.0000059604644775,
					"bytes":	9175040,
					"bits_per_second":	73399882.502607688,
					"retransmits":	0,
					"snd_cwnd":	2975640,
					"rtt":	321945,
					"rttvar":	1535,
					"pmtu":	1500,
					"omitted":	false
				}],
			"sum":	{
				"start":	14.00012993812561,
				"end":	15.000135898590088,
				"seconds":	1.0000059604644775,
				"bytes":	9175040,
				"bits_per_second":	73399882.502607688,
				"retransmits":	0,
				"omitted":	false
			}
		}, {
			"streams":	[{
					"socket":	6,
					"start":	15.000135898590088,
					"end":	16.000089883804321,
					"seconds":	0.9999539852142334,
					"bytes":	9175040,
					"bits_per_second":	73403697.655422091,
					"retransmits":	0,
					"snd_cwnd":	3066864,
					"rtt":	311830,
					"rttvar":	1743,
					"pmtu":	1500,
					"omitted":	false
				}],
			"sum":	{
				"start":	15.000135898590088,
				"end":	16.000089883804321,
				"seconds":	0.9999539852142334,
				"bytes":	9175040,
				"bits_per_second":	73403697.655422091,
				"retransmits":	0,
				"omitted":	false
			}
		}, {
			"streams":	[{
					"socket":	6,
					"start":	16.000089883804321,
					"end":	17.000082969665527,
					"seconds":	0.999993085861206,
					"bytes":	9175040,
					"bits_per_second":	73400827.503508955,
					"retransmits":	0,
					"snd_cwnd":	3130576,
					"rtt":	365075,
					"rttvar":	4035,
					"pmtu":	1500,
					"omitted":	false
				}],
			"sum":	{
				"start":	16.000089883804321,
				"end":	17.000082969665527,
				"seconds":	0.999993085861206,
				"bytes":	9175040,
				"bits_per_second":	73400827.503508955,
				"retransmits":	0,
				"omitted":	false
			}
		}, {
			"streams":	[{
					"socket":	6,
					"start":	17.000082969665527,
					"end":	18.000052928924561,
					"seconds":	0.9999699592590332,
					"bytes":	9175040,
					"bits_per_second":	73402525.066241831,
					"retransmits":	0,
					"snd_cwnd":	3176912,
					"rtt":	418595,
					"rttvar":	2957,
					"pmtu":	1500,
					"omitted":	false
				}],
			"sum":	{
				"start":	17.000082969665527,
				"end":	18.000052928924561,
				"seconds":	0.9999699592590332,
				"bytes":	9175040,
				"bits_per_second":	73402525.066241831,
				"retransmits":	0,
				"omitted":	false
			}
		}, {
			"streams":	[{
					"socket":	6,
					"start":	18.000052928924561,
					"end":	19.000103950500488,
					"seconds":	1.0000510215759277,
					"bytes":	7864320,
					"bits_per_second":	62911350.1637709,
					"retransmits":	0,
					"snd_cwnd":	3208768,
					"rtt":	311956,
					"rttvar":	2108,
					"pmtu":	1500,
					"omitted":	false
				}],
			"sum":	{
				"start":	18.000052928924561,
				"end":	19.000103950500488,
				"seconds":	1.0000510215759277,
				"bytes":	7864320,
				"bits_per_second":	62911350.1637709,
				"retransmits":	0,
				"omitted":	false
			}
		}, {
			"streams":	[{
					"socket":	6,
					"start":	19.000103950500488,
					"end":	20.000102996826172,
					"seconds":	0.99999904632568359,
					"bytes":	9175040,
					"bits_per_second":	73400390.000066757,
					"retransmits":	0,
					"snd_cwnd":	3226144,
					"rtt":	389846,
					"rttvar":	896,
					"pmtu":	1500,
					"omitted":	false
				}],
			"sum":	{
				"start":	19.000103950500488,
				"end":	20.000102996826172,
				"seconds":	0.99999904632568359,
				"bytes":	9175040,
				"bits_per_second":	73400390.000066757,
				"retransmits":	0,
				"omitted":	false
			}
		}, {
			"streams":	[{
					"socket":	6,
					"start":	20.000102996826172,
					"end":	21.00006890296936,
					"seconds":	0.99996590614318848,
					"bytes":	7864320,
					"bits_per_second":	62916705.073133819,
					"retransmits":	0,
					"snd_cwnd":	3234832,
					"rtt":	401248,
					"rttvar":	536,
					"pmtu":	1500,
					"omitted":	false
				}],
			"sum":	{
				"start":	20.000102996826172,
				"end":	21.00006890296936,
				"seconds":	0.99996590614318848,
				"bytes":	7864320,
				"bits_per_second":	62916705.073133819,
				"retransmits":	0,
				"omitted":	false
			}
		}, {
			"streams":	[{
					"socket":	6,
					"start":	21.00006890296936,
					"end":	22.000118970870972,
					"seconds":	1.0000500679016113,
					"bytes":	7864320,
					"bits_per_second":	62911410.157705992,
					"retransmits":	0,
					"snd_cwnd":	3237728,
					"rtt":	391216,
					"rttvar":	3999,
					"pmtu":	1500,
					"omitted":	false
				}],
			"sum":	{
				"start":	21.00006890296936,
				"end":	22.000118970870972,
				"seconds":	1.0000500679016113,
				"bytes":	7864320,
				"bits_per_second":	62911410.157705992,
				"retransmits":	0,
				"omitted":	false
			}
		}, {
			"streams":	[{
					"socket":	6,
					"start":	22.000118970870972,
					"end":	23.000066041946411,
					"seconds":	0.99994707107543945,
					"bytes":	7864320,
					"bits_per_second":	62917890.176262647,
					"retransmits":	0,
					"snd_cwnd":	3237728,
					"rtt":	405400,
					"rttvar":	342,
					"pmtu":	1500,
					"omitted":	false
				}],
			"sum":	{
				"start":	22.000118970870972,
				"end":	23.000066041946411,
				"seconds":	0.99994707107543945,
				"bytes":	7864320,
				"bits_per_second":	62917890.176262647,
				"retransmits":	0,
				"omitted":	false
			}
		}, {
			"streams":	[{
					"socket":	6,
					"start":	23.000066041946411,
					"end":	24.000086069107056,
					"seconds":	1.0000200271606445,
					"bytes":	9175040,
					"bits_per_second":	73398850.02943933,
					"retransmits":	0,
					"snd_cwnd":	3239176,
					"rtt":	386544,
					"rttvar":	5579,
					"pmtu":	1500,
					"omitted":	false
				}],
			"sum":	{
				"start":	23.000066041946411,
				"end":	24.000086069107056,
				"seconds":	1.0000200271606445,
				"bytes":	9175040,
				"bits_per_second":	73398850.02943933,
				"retransmits":	0,
				"omitted":	false
			}
		}, {
			"streams":	[{
					"socket":	6,
					"start":	24.000086069107056,
					"end":	25.000067949295044,
					"seconds":	0.99998188018798828,
					"bytes":	9175040,
					"bits_per_second":	73401650.024099782,
					"retransmits":	0,
					"snd_cwnd":	3244968,
					"rtt":	398619,
					"rttvar":	107,
					"pmtu":	1500,
					"omitted":	false
				}],
			"sum":	{
				"start":	24.000086069107056,
				"end":	25.000067949295044,
				"seconds":	0.99998188018798828,
				"bytes":	9175040,
				"bits_per_second":	73401650.024099782,
				"retransmits":	0,
				"omitted":	false
			}
		}, {
			"streams":	[{
					"socket":	6,
					"start":	25.000067949295044,
					"end":	26.000070095062256,
					"seconds":	1.0000021457672119,
					"bytes":	6553600,
					"bits_per_second":	52428687.5002414,
					"retransmits":	0,
					"snd_cwnd":	3258000,
					"rtt":	395778,
					"rttvar":	2991,
					"pmtu":	1500,
					"omitted":	false
				}],
			"sum":	{
				"start":	25.000067949295044,
				"end":	26.000070095062256,
				"seconds":	1.0000021457672119,
				"bytes":	6553600,
				"bits_per_second":	52428687.5002414,
				"retransmits":	0,
				"omitted":	false
			}
		}, {
			"streams":	[{
					"socket":	6,
					"start":	26.000070095062256,
					"end":	26.617997884750366,
					"seconds":	0.61792778968811035,
					"bytes":	6553600,
					"bits_per_second":	84846159.8182251,
					"retransmits":	0,
					"snd_cwnd":	2300872,
					"rtt":	344188,
					"rttvar":	2288,
					"pmtu":	1500,
					"omitted":	false
				}],
			"sum":	{
				"start":	26.000070095062256,
				"end":	26.617997884750366,
				"seconds":	0.61792778968811035,
				"bytes":	6553600,
				"bits_per_second":	84846159.8182251,
				"retransmits":	0,
				"omitted":	false
			}
		}],
	"end":	{
		"streams":	[{
				"sender":	{
					"socket":	6,
					"start":	0,
					"end":	26.617997884750366,
					"seconds":	26.617997884750366,
					"bytes":	210663408,
					"bits_per_second":	63314576.524387062,
					"retransmits":	0,
					"max_snd_cwnd":	3258000,
					"max_rtt":	418595,
					"min_rtt":	131940,
					"mean_rtt":	309314
				},
				"receiver":	{
					"socket":	6,
					"start":	0,
					"end":	27.158430814743042,
					"seconds":	26.617997884750366,
					"bytes":	201134440,
					"bits_per_second":	59247735.297228888
				}
			}],
		"sum_sent":	{
			"start":	0,
			"end":	26.617997884750366,
			"seconds":	26.617997884750366,
			"bytes":	210663408,
			"bits_per_second":	63314576.524387062,
			"retransmits":	0
		},
		"sum_received":	{
			"start":	0,
			"end":	27.158430814743042,
			"seconds":	27.158430814743042,
			"bytes":	201134440,
			"bits_per_second":	59247735.297228888
		},
		"cpu_utilization_percent":	{
			"host_total":	1.7212551078255349,
			"host_user":	0.22339013747339218,
			"host_system":	1.4978543256300674,
			"remote_total":	0.429796428036699,
			"remote_user":	0.040487034023749396,
			"remote_system":	0.38930677255974461
		},
		"sender_tcp_congestion":	"cubic",
		"receiver_tcp_congestion":	"cubic"
	}
}
